oneliner_utils/__init__.py
oneliner_utils/handlers/__init__.py
oneliner_utils/handlers/common.py
oneliner_utils/handlers/csv_handler.py
oneliner_utils/handlers/gzip_handler.py
oneliner_utils/handlers/json_handler.py
oneliner_utils/handlers/jsonl_handler.py
oneliner_utils/handlers/list_handler.py
oneliner_utils/handlers/lz4_handler.py
oneliner_utils/handlers/numpy_handler.py
oneliner_utils/handlers/path_handler.py
oneliner_utils/handlers/pickle_handler.py
oneliner_utils/handlers/string_handler.py
oneliner_utils-0.1.2.dist-info/LICENSE
oneliner_utils-0.1.2.dist-info/METADATA
oneliner_utils-0.1.2.dist-info/WHEEL
oneliner_utils-0.1.2.dist-info/top_level.txt
oneliner_utils-0.1.2.dist-info/RECORD
