Metadata-Version: 2.1
Name: oneliner-utils
Version: 0.1.2
Summary: One-line Utils for Python
Home-page: https://github.com/AmenRa/oneliner-utils
Author: Elias Bassani
Author-email: elias.bssn@gmail.com
Keywords: oneliner,oneliners,utils,utilities
Classifier: Programming Language :: Python :: 3
Classifier: License :: OSI Approved :: MIT License
Classifier: Intended Audience :: Science/Research
Classifier: Operating System :: OS Independent
Classifier: Topic :: Text Processing :: General
Requires-Python: >=3.7
License-File: LICENSE
Requires-Dist: numpy
Requires-Dist: orjson
Requires-Dist: lz4
